smartflow/__init__.py
smartflow/client.py
smartflow/exceptions.py
smartflow/sync.py
smartflow/types.py
smartflow_sdk-0.2.0.dist-info/licenses/LICENSE
smartflow_sdk-0.2.0.dist-info/METADATA
smartflow_sdk-0.2.0.dist-info/WHEEL
smartflow_sdk-0.2.0.dist-info/top_level.txt
smartflow_sdk-0.2.0.dist-info/RECORD
