Metadata-Version: 2.4
Name: smartflow-sdk
Version: 0.2.0
Summary: Developer SDK for Smartflow AI orchestration, caching, compliance, and governance
Author-email: "Langsmart, Inc." <scott@sragrouptx.com>
License-Expression: MIT
Project-URL: Homepage, https://smartflow.ai
Project-URL: Documentation, https://docs.smartflow.ai/sdk/python
Project-URL: Repository, https://github.com/langsmart/smartflow-sdk-python
Project-URL: Changelog, https://github.com/langsmart/smartflow-sdk-python/blob/main/CHANGELOG.md
Project-URL: Issues, https://github.com/langsmart/smartflow-sdk-python/issues
Keywords: ai,llm,openai,anthropic,claude,gpt,caching,compliance,governance,orchestration,proxy,agents,ml,enterprise
Classifier: Development Status :: 4 - Beta
Classifier: Intended Audience :: Developers
Classifier: Operating System :: OS Independent
Classifier: Programming Language :: Python :: 3
Classifier: Programming Language :: Python :: 3.9
Classifier: Programming Language :: Python :: 3.10
Classifier: Programming Language :: Python :: 3.11
Classifier: Programming Language :: Python :: 3.12
Classifier: Topic :: Software Development :: Libraries :: Python Modules
Classifier: Topic :: Scientific/Engineering :: Artificial Intelligence
Requires-Python: >=3.9
License-File: LICENSE
Requires-Dist: httpx>=0.25.0
Provides-Extra: dev
Requires-Dist: pytest>=7.0; extra == "dev"
Requires-Dist: pytest-asyncio>=0.21; extra == "dev"
Requires-Dist: pytest-cov>=4.0; extra == "dev"
Requires-Dist: black>=23.0; extra == "dev"
Requires-Dist: ruff>=0.1; extra == "dev"
Requires-Dist: mypy>=1.0; extra == "dev"
Provides-Extra: nest
Requires-Dist: nest-asyncio>=1.5; extra == "nest"
Dynamic: license-file
